pydid/__init__.py
pydid/common.py
pydid/did.py
pydid/did_url.py
pydid/doc/__init__.py
pydid/doc/builder.py
pydid/doc/corrections.py
pydid/doc/doc.py
pydid/doc/generic.py
pydid/resource.py
pydid/service.py
pydid/validation.py
pydid/verification_method.py
pydid-0.5.2.dist-info/LICENSE
pydid-0.5.2.dist-info/METADATA
pydid-0.5.2.dist-info/WHEEL
pydid-0.5.2.dist-info/RECORD
